aes_gcm_txt_enc_lib/__init__.py
aes_gcm_txt_enc_lib/__main__.py
aes_gcm_txt_enc_lib/aes_gcm_encryptor.py
aes_gcm_txt_enc_lib/core.py
aes_gcm_txt_enc_lib-0.2.0.dist-info/LICENSE
aes_gcm_txt_enc_lib-0.2.0.dist-info/METADATA
aes_gcm_txt_enc_lib-0.2.0.dist-info/WHEEL
aes_gcm_txt_enc_lib-0.2.0.dist-info/RECORD
