Metadata-Version: 2.3
Name: aes-gcm-txt-enc-lib
Version: 0.2.0
Summary: Python library for symmetric key based secure text encryption and decryption using AES-GCM.
Author: Komal Singh
Author-email: komalsin9h@gmail.com
Requires-Python: >=3.6
Classifier: Programming Language :: Python :: 3
Classifier: Programming Language :: Python :: 3.6
Classifier: Programming Language :: Python :: 3.7
Classifier: Programming Language :: Python :: 3.8
Classifier: Programming Language :: Python :: 3.9
Classifier: Programming Language :: Python :: 3.10
Classifier: Programming Language :: Python :: 3.11
Classifier: Programming Language :: Python :: 3.12
Classifier: Programming Language :: Python :: 3.13
Requires-Dist: pycryptodome (>=3.23.0,<4.0.0)
